flute/__init__.py
flute/Modules/AbstractPromptProcessor.py
flute/Modules/ClaudePromptProcessor.py
flute/Modules/GPTPromptProcessor.py
flute/Modules/GeminiPromptProcessor.py
flute/Modules/PromptProcessorFactory.py
flute/Modules/__init__.py
flute/Modules/__pycache__/AbstractPromptProcessor.cpython-311.pyc
flute/Modules/__pycache__/ClaudePromptProcessor.cpython-311.pyc
flute/Modules/__pycache__/GPTPromptProcessor.cpython-311.pyc
flute/Modules/__pycache__/GeminiPromptProcessor.cpython-311.pyc
flute/Modules/__pycache__/PromptProcessorFactory.cpython-311.pyc
flute/Modules/__pycache__/__init__.cpython-311.pyc
flute/Test/__init__.py
flute/Test/test_prompt_processors.py
flute/Test/__pycache__/__init__.cpython-311.pyc
flute/Test/__pycache__/test_prompt_processors.cpython-311-pytest-8.2.1.pyc
flute/__pycache__/__init__.cpython-311.pyc
FLUTE_LLM-0.1.6.dist-info/LICENSE
FLUTE_LLM-0.1.6.dist-info/METADATA
FLUTE_LLM-0.1.6.dist-info/WHEEL
FLUTE_LLM-0.1.6.dist-info/top_level.txt
FLUTE_LLM-0.1.6.dist-info/RECORD
