Metadata-Version: 2.1
Name: FLUTE-LLM
Version: 0.1.6
Summary: A package for prompt processing and language model interaction
Home-page: https://github.com/thepioneerjp/FLUTE
Author: The Pioneer
Classifier: Development Status :: 3 - Alpha
Classifier: Intended Audience :: Developers
Classifier: Programming Language :: Python :: 3
License-File: LICENSE
Requires-Dist: openai
Requires-Dist: anthropic
Requires-Dist: google-generativeai
Requires-Dist: python-dotenv
Requires-Dist: pytest
